README.rst
setup.py
autoworker/__init__.py
autoworker.egg-info/PKG-INFO
autoworker.egg-info/SOURCES.txt
autoworker.egg-info/dependency_links.txt
autoworker.egg-info/requires.txt
autoworker.egg-info/top_level.txt
spec/__init__.py
spec/autoworker_spec.py
spec/enq.py
spec/test.py