Metadata-Version: 1.1
Name: autoworker
Version: 0.6.0
Summary: Start Python RQ Workers automatically
Home-page: https://github.com/gisce/autoworker
Author: GISCE-TI, S.L.
Author-email: devel@gisce.net
License: MIT
Platform: UNKNOWN
Classifier: Programming Language :: Python
Classifier: Programming Language :: Python :: 2.7
Classifier: Programming Language :: Python :: 3.5
